pump_fun_launcher/__init__.py
pump_fun_launcher/config.py
pump_fun_launcher/constants.py
pump_fun_launcher/instructions.py
pump_fun_launcher/launcher.py
pump_fun_launcher/types.py
pump_fun_launcher/utils.py
pump_fun_token_launcher-1.0.0.dist-info/METADATA
pump_fun_token_launcher-1.0.0.dist-info/WHEEL
pump_fun_token_launcher-1.0.0.dist-info/top_level.txt
pump_fun_token_launcher-1.0.0.dist-info/RECORD
