Metadata-Version: 2.4
Name: pump-fun-token-launcher
Version: 1.0.0
Summary: Programmatically launch pump.fun tokens with Python support
Home-page: https://github.com/bilix-software/pump-fun-token-launcher-python
Author: Bilix Software
Author-email: Bilix Software <info@bilix.io>
License: MIT
Project-URL: Homepage, https://github.com/bilix-software/pump-fun-token-launcher-python
Project-URL: Bug Reports, https://github.com/bilix-software/pump-fun-token-launcher-python/issues
Project-URL: Source, https://github.com/bilix-software/pump-fun-token-launcher-python
Project-URL: Documentation, https://github.com/bilix-software/pump-fun-token-launcher-python#readme
Keywords: pump.fun,solana,token,crypto,blockchain,defi
Classifier: Development Status :: 4 - Beta
Classifier: Intended Audience :: Developers
Classifier: License :: OSI Approved :: MIT License
Classifier: Operating System :: OS Independent
Classifier: Programming Language :: Python :: 3
Classifier: Programming Language :: Python :: 3.8
Classifier: Programming Language :: Python :: 3.9
Classifier: Programming Language :: Python :: 3.10
Classifier: Programming Language :: Python :: 3.11
Classifier: Programming Language :: Python :: 3.12
Classifier: Topic :: Software Development :: Libraries :: Python Modules
Classifier: Topic :: Internet :: WWW/HTTP
Classifier: Topic :: Office/Business :: Financial
Requires-Python: >=3.8
Requires-Dist: solana>=0.30.0
Requires-Dist: solders>=0.20.0
Requires-Dist: construct>=2.10.0
Requires-Dist: base58>=2.1.0
Requires-Dist: httpx>=0.24.0
Requires-Dist: anchorpy>=0.19.0
Provides-Extra: dev
Requires-Dist: pytest>=7.0.0; extra == "dev"
Requires-Dist: pytest-asyncio>=0.21.0; extra == "dev"
Requires-Dist: black>=23.0.0; extra == "dev"
Requires-Dist: isort>=5.12.0; extra == "dev"
Requires-Dist: mypy>=1.0.0; extra == "dev"
Dynamic: author
Dynamic: home-page
Dynamic: requires-python
